sensibull_quotes/__init__.py
sensibull_quotes/quotes.py
sensibull_quotes-0.1.0.dist-info/LICENSE
sensibull_quotes-0.1.0.dist-info/METADATA
sensibull_quotes-0.1.0.dist-info/WHEEL
sensibull_quotes-0.1.0.dist-info/top_level.txt
sensibull_quotes-0.1.0.dist-info/RECORD
