Metadata-Version: 2.1
Name: sensibull_quotes
Version: 0.1.0
Summary: A Python package to fetch and process live derivative prices and quotes from Sensibull's API
Home-page: https://github.com/itsundef/sensibull_quotes
Author: Prashant Kumar
Author-email: its@undef.in
Classifier: Programming Language :: Python :: 3
Classifier: License :: OSI Approved :: MIT License
Classifier: Operating System :: OS Independent
Requires-Python: >=3.6
License-File: LICENSE
Requires-Dist: requests>=2.25.1
